setup.py
vcnadera/__init__.py
vcnadera/backbone.py
vcnadera/eval_class_v63.py
vcnadera/main.py
vcnadera/nadera_class_v63.py
vcnadera/yolact.py
vcnadera.egg-info/PKG-INFO
vcnadera.egg-info/SOURCES.txt
vcnadera.egg-info/dependency_links.txt
vcnadera.egg-info/requires.txt
vcnadera.egg-info/top_level.txt
vcnadera/data/__init__.py
vcnadera/data/coco.py
vcnadera/data/config.py
vcnadera/layers/__init__.py
vcnadera/layers/box_utils.py
vcnadera/layers/interpolate.py
vcnadera/layers/output_utils.py
vcnadera/layers/functions/__init__.py
vcnadera/layers/functions/detection.py
vcnadera/layers/modules/__init__.py
vcnadera/layers/modules/multibox_loss.py
vcnadera/utils/__init__.py
vcnadera/utils/augmentations.py
vcnadera/utils/cython_nms.pyx
vcnadera/utils/functions.py
vcnadera/utils/timer.py
vcnadera/weights1/emes.png
vcnadera/weights2/emes.png
vcnadera/weights2/nadera_model_v6.3.json
vcnadera/weights2/nadera_weight_v6.3.h5