Metadata-Version: 1.0
Name: vcnadera
Version: 0.1.9
Summary: Nadera by Viniette & Clarity.
Home-page: https://www.nadera.me/
Author: Shoya Yasuda @ Viniette & Clarity, Inc.
Author-email: selamatpagi1124@gmail.com
License: Required: Copyright notice in any social outputs.     Permitted: Private Use, Commercial Use.     Forbidden: Sublicense, Modifications, Distribution, Patent Grant, Use Trademark, Hold Liable.
Platform: UNKNOWN
